{
 "PRed":[
  {
   "data":{
    "bot_rerun":false,
    "migrator_name":"Version",
    "migrator_version":0,
    "version":"0.3.1"
   },
   "keys":[
    "bot_rerun",
    "migrator_name",
    "migrator_version",
    "version"
   ]
  },
  {
   "PR":{
    "__lazy_json__":"pr_json/206987576.json"
   },
   "data":{
    "bot_rerun":false,
    "migrator_name":"Version",
    "migrator_version":0,
    "version":"0.4.0"
   },
   "keys":[
    "bot_rerun",
    "migrator_name",
    "migrator_version",
    "version"
   ]
  },
  {
   "PR":{
    "__lazy_json__":"pr_json/207295917.json"
   },
   "data":{
    "bot_rerun":false,
    "migrator_name":"Version",
    "migrator_version":0,
    "version":"0.4.1"
   },
   "keys":[
    "bot_rerun",
    "migrator_name",
    "migrator_version",
    "version"
   ]
  },
  {
   "PR":{
    "__lazy_json__":"pr_json/225103874.json"
   },
   "data":{
    "bot_rerun":false,
    "migrator_name":"Version",
    "migrator_version":0,
    "version":"0.5.0"
   },
   "keys":[
    "bot_rerun",
    "migrator_name",
    "migrator_version",
    "version"
   ]
  },
  {
   "PR":{
    "__lazy_json__":"pr_json/263895062.json"
   },
   "data":{
    "bot_rerun":false,
    "migrator_name":"Version",
    "migrator_version":0,
    "version":"0.5.1"
   },
   "keys":[
    "bot_rerun",
    "migrator_name",
    "migrator_version",
    "version"
   ]
  },
  {
   "PR":{
    "__lazy_json__":"pr_json/328401906.json"
   },
   "data":{
    "bot_rerun":1591816407.8809862,
    "migrator_name":"Version",
    "migrator_version":0,
    "version":"0.5.2"
   },
   "keys":[
    "bot_rerun",
    "migrator_name",
    "migrator_version",
    "version"
   ]
  },
  {
   "PR":{
    "__lazy_json__":"pr_json/335828985.json"
   },
   "data":{
    "bot_rerun":false,
    "migrator_name":"MigrationYaml",
    "migrator_object_version":1,
    "migrator_version":0,
    "name":"python38"
   },
   "keys":[
    "bot_rerun",
    "migrator_name",
    "migrator_object_version",
    "migrator_version",
    "name"
   ]
  },
  {
   "PR":{
    "__lazy_json__":"pr_json/389657080.json"
   },
   "data":{
    "bot_rerun":false,
    "migrator_name":"MigrationYaml",
    "migrator_object_version":1,
    "migrator_version":0,
    "name":"pypy"
   },
   "keys":[
    "bot_rerun",
    "migrator_name",
    "migrator_object_version",
    "migrator_version",
    "name"
   ]
  },
  {
   "PR":{
    "__lazy_json__":"pr_json/432673376.json"
   },
   "data":{
    "bot_rerun":false,
    "migrator_name":"Version",
    "migrator_version":0,
    "version":"0.5.2"
   },
   "keys":[
    "bot_rerun",
    "migrator_name",
    "migrator_version",
    "version"
   ]
  }
 ],
 "archived":false,
 "bad":false,
 "conda-forge.yml":{
  "provider":{
   "win":"azure"
  }
 },
 "feedstock_name":"click-completion",
 "hash_type":"sha256",
 "linux_64_meta_yaml":{
  "about":{
   "description":"Enhanced completion for Click\nAdd automatic completion support for fish, Zsh, Bash and PowerShell to Click.\nAll the supported shells are able to complete all the command line arguments\nand options defined with click. In addition, fish and Zsh are also displaying\nthe options and commands help during the completion.\n",
   "dev_url":"https://github.com/click-contrib/click-completion",
   "doc_url":"https://github.com/click-contrib/click-completion",
   "home":"https://github.com/click-contrib/click-completion",
   "license":"MIT",
   "license_family":"MIT",
   "license_file":"LICENSE",
   "summary":"Fish, Bash, Zsh and PowerShell completion for Click"
  },
  "build":{
   "number":"0",
   "script":"-m pip install . --no-deps -vv"
  },
  "extra":{
   "recipe-maintainers":[
    "epruesse"
   ]
  },
  "package":{
   "name":"click-completion",
   "version":"0.5.2"
  },
  "requirements":{
   "build":[
    "python",
    "pip",
    "setuptools"
   ],
   "run":[
    "python",
    "six",
    "click",
    "jinja2",
    "shellingham"
   ]
  },
  "source":{
   "fn":"click-completion-0.5.2.tar.gz",
   "sha256":"5bf816b81367e638a190b6e91b50779007d14301b3f9f3145d68e3cade7bce86",
   "url":"https://pypi.io/packages/source/c/click-completion/click-completion-0.5.2.tar.gz"
  },
  "test":{
   "imports":[
    "click_completion"
   ]
  }
 },
 "linux_64_requirements":{
  "build":{
   "__set__":true,
   "elements":[
    "pip",
    "python",
    "setuptools"
   ]
  },
  "host":{
   "__set__":true,
   "elements":[]
  },
  "run":{
   "__set__":true,
   "elements":[
    "click",
    "jinja2",
    "python",
    "shellingham",
    "six"
   ]
  },
  "test":{
   "__set__":true,
   "elements":[]
  }
 },
 "meta_yaml":{
  "about":{
   "description":"Enhanced completion for Click\nAdd automatic completion support for fish, Zsh, Bash and PowerShell to Click.\nAll the supported shells are able to complete all the command line arguments\nand options defined with click. In addition, fish and Zsh are also displaying\nthe options and commands help during the completion.\n",
   "dev_url":"https://github.com/click-contrib/click-completion",
   "doc_url":"https://github.com/click-contrib/click-completion",
   "home":"https://github.com/click-contrib/click-completion",
   "license":"MIT",
   "license_family":"MIT",
   "license_file":"LICENSE",
   "summary":"Fish, Bash, Zsh and PowerShell completion for Click"
  },
  "build":{
   "number":"0",
   "script":"-m pip install . --no-deps -vv"
  },
  "extra":{
   "recipe-maintainers":[
    "epruesse",
    "epruesse",
    "epruesse"
   ]
  },
  "package":{
   "name":"click-completion",
   "version":"0.5.2"
  },
  "requirements":{
   "build":[
    "python",
    "pip",
    "setuptools",
    "python",
    "pip",
    "setuptools",
    "python",
    "pip",
    "setuptools"
   ],
   "run":[
    "python",
    "six",
    "click",
    "jinja2",
    "shellingham",
    "python",
    "six",
    "click",
    "jinja2",
    "shellingham",
    "python",
    "six",
    "click",
    "jinja2",
    "shellingham"
   ]
  },
  "source":{
   "fn":"click-completion-0.5.2.tar.gz",
   "sha256":"5bf816b81367e638a190b6e91b50779007d14301b3f9f3145d68e3cade7bce86",
   "url":"https://pypi.io/packages/source/c/click-completion/click-completion-0.5.2.tar.gz"
  },
  "test":{
   "imports":[
    "click_completion",
    "click_completion",
    "click_completion"
   ]
  }
 },
 "name":"click-completion",
 "new_version":"0.5.2",
 "new_version_attempts":{
  "0.5.2":1
 },
 "new_version_errors":{},
 "osx_64_meta_yaml":{
  "about":{
   "description":"Enhanced completion for Click\nAdd automatic completion support for fish, Zsh, Bash and PowerShell to Click.\nAll the supported shells are able to complete all the command line arguments\nand options defined with click. In addition, fish and Zsh are also displaying\nthe options and commands help during the completion.\n",
   "dev_url":"https://github.com/click-contrib/click-completion",
   "doc_url":"https://github.com/click-contrib/click-completion",
   "home":"https://github.com/click-contrib/click-completion",
   "license":"MIT",
   "license_family":"MIT",
   "license_file":"LICENSE",
   "summary":"Fish, Bash, Zsh and PowerShell completion for Click"
  },
  "build":{
   "number":"0",
   "script":"-m pip install . --no-deps -vv"
  },
  "extra":{
   "recipe-maintainers":[
    "epruesse"
   ]
  },
  "package":{
   "name":"click-completion",
   "version":"0.5.2"
  },
  "requirements":{
   "build":[
    "python",
    "pip",
    "setuptools"
   ],
   "run":[
    "python",
    "six",
    "click",
    "jinja2",
    "shellingham"
   ]
  },
  "source":{
   "fn":"click-completion-0.5.2.tar.gz",
   "sha256":"5bf816b81367e638a190b6e91b50779007d14301b3f9f3145d68e3cade7bce86",
   "url":"https://pypi.io/packages/source/c/click-completion/click-completion-0.5.2.tar.gz"
  },
  "test":{
   "imports":[
    "click_completion"
   ]
  }
 },
 "osx_64_requirements":{
  "build":{
   "__set__":true,
   "elements":[
    "pip",
    "python",
    "setuptools"
   ]
  },
  "host":{
   "__set__":true,
   "elements":[]
  },
  "run":{
   "__set__":true,
   "elements":[
    "click",
    "jinja2",
    "python",
    "shellingham",
    "six"
   ]
  },
  "test":{
   "__set__":true,
   "elements":[]
  }
 },
 "pinning_version":"2020.06.07.16.42.19",
 "raw_meta_yaml":"{% set name = \"click-completion\" %}\n{% set version = \"0.5.2\" %}\n{% set sha256 = \"5bf816b81367e638a190b6e91b50779007d14301b3f9f3145d68e3cade7bce86\" %}\n\npackage:\n  name: {{ name|lower }}\n  version: {{ version }}\n\nsource:\n  fn: {{ name }}-{{ version }}.tar.gz\n  url: https://pypi.io/packages/source/{{ name[0] }}/{{ name }}/{{ name }}-{{ version }}.tar.gz\n  sha256: {{ sha256 }}\n\nbuild:\n  number: 0\n  script: {{ PYTHON }} -m pip install . --no-deps -vv\n\nrequirements:\n  build:\n    - python\n    - pip\n    - setuptools\n\n  run:\n    - python\n    - six\n    - click\n    - jinja2\n    - enum34  # [ py < 30 ]\n    - shellingham\n\ntest:\n  imports:\n    - click_completion\n\nabout:\n  home: https://github.com/click-contrib/click-completion\n  license: MIT\n  license_family: MIT\n  license_file: LICENSE\n  summary: Fish, Bash, Zsh and PowerShell completion for Click\n\n  description: |\n    Enhanced completion for Click\n    Add automatic completion support for fish, Zsh, Bash and PowerShell to Click.\n    All the supported shells are able to complete all the command line arguments\n    and options defined with click. In addition, fish and Zsh are also displaying\n    the options and commands help during the completion.\n  doc_url: https://github.com/click-contrib/click-completion\n  dev_url: https://github.com/click-contrib/click-completion\n\nextra:\n  recipe-maintainers:\n    - epruesse\n",
 "req":{
  "__set__":true,
  "elements":[
   "click",
   "jinja2",
   "pip",
   "python",
   "setuptools",
   "shellingham",
   "six"
  ]
 },
 "requirements":{
  "build":{
   "__set__":true,
   "elements":[
    "pip",
    "python",
    "setuptools"
   ]
  },
  "host":{
   "__set__":true,
   "elements":[]
  },
  "run":{
   "__set__":true,
   "elements":[
    "click",
    "jinja2",
    "python",
    "shellingham",
    "six"
   ]
  },
  "test":{
   "__set__":true,
   "elements":[]
  }
 },
 "smithy_version":"No azure token. Create a token and\nput it in ~/.conda-smithy/azure.token\n3.7.3\n",
 "strong_exports":false,
 "total_requirements":{
  "build":{
   "__set__":true,
   "elements":[
    "pip",
    "python",
    "setuptools"
   ]
  },
  "host":{
   "__set__":true,
   "elements":[]
  },
  "run":{
   "__set__":true,
   "elements":[
    "click",
    "jinja2",
    "python",
    "shellingham",
    "six"
   ]
  },
  "test":{
   "__set__":true,
   "elements":[]
  }
 },
 "url":"https://pypi.io/packages/source/c/click-completion/click-completion-0.5.1.tar.gz",
 "version":"0.5.2",
 "win_64_meta_yaml":{
  "about":{
   "description":"Enhanced completion for Click\nAdd automatic completion support for fish, Zsh, Bash and PowerShell to Click.\nAll the supported shells are able to complete all the command line arguments\nand options defined with click. In addition, fish and Zsh are also displaying\nthe options and commands help during the completion.\n",
   "dev_url":"https://github.com/click-contrib/click-completion",
   "doc_url":"https://github.com/click-contrib/click-completion",
   "home":"https://github.com/click-contrib/click-completion",
   "license":"MIT",
   "license_family":"MIT",
   "license_file":"LICENSE",
   "summary":"Fish, Bash, Zsh and PowerShell completion for Click"
  },
  "build":{
   "number":"0",
   "script":"-m pip install . --no-deps -vv"
  },
  "extra":{
   "recipe-maintainers":[
    "epruesse"
   ]
  },
  "package":{
   "name":"click-completion",
   "version":"0.5.2"
  },
  "requirements":{
   "build":[
    "python",
    "pip",
    "setuptools"
   ],
   "run":[
    "python",
    "six",
    "click",
    "jinja2",
    "shellingham"
   ]
  },
  "source":{
   "fn":"click-completion-0.5.2.tar.gz",
   "sha256":"5bf816b81367e638a190b6e91b50779007d14301b3f9f3145d68e3cade7bce86",
   "url":"https://pypi.io/packages/source/c/click-completion/click-completion-0.5.2.tar.gz"
  },
  "test":{
   "imports":[
    "click_completion"
   ]
  }
 },
 "win_64_requirements":{
  "build":{
   "__set__":true,
   "elements":[
    "pip",
    "python",
    "setuptools"
   ]
  },
  "host":{
   "__set__":true,
   "elements":[]
  },
  "run":{
   "__set__":true,
   "elements":[
    "click",
    "jinja2",
    "python",
    "shellingham",
    "six"
   ]
  },
  "test":{
   "__set__":true,
   "elements":[]
  }
 }
}