{
 "archived":false,
 "bad":false,
 "conda-forge.yml":{},
 "feedstock_name":"django-cognito-jwt",
 "hash_type":"sha256",
 "linux_64_meta_yaml":{
  "about":{
   "home":"https://github.com/labd/django-cognito-jwt",
   "license":"MIT",
   "license_family":"MIT",
   "license_file":"LICENSE",
   "summary":"An Authentication backend for Django Rest Framework for AWS Cognito JWT tokens"
  },
  "build":{
   "noarch":"python",
   "number":"0",
   "script":" -m pip install . -vv"
  },
  "extra":{
   "recipe-maintainers":[
    "hadim"
   ]
  },
  "package":{
   "name":"django-cognito-jwt",
   "version":"0.0.3"
  },
  "requirements":{
   "host":[
    "python",
    "pip"
   ],
   "run":[
    "python",
    "django >=1.11",
    "cryptography",
    "djangorestframework",
    "pyjwt",
    "requests"
   ]
  },
  "source":{
   "sha256":"6e9dfb79b262c338a493b71f81811621f88fb0af88d4b86e896252a9c00c81bf",
   "url":"https://pypi.io/packages/source/d/django-cognito-jwt/django-cognito-jwt-0.0.3.tar.gz"
  },
  "test":{
   "imports":[
    "django_cognito_jwt"
   ]
  }
 },
 "linux_64_requirements":{
  "build":{
   "__set__":true,
   "elements":[]
  },
  "host":{
   "__set__":true,
   "elements":[
    "pip",
    "python"
   ]
  },
  "run":{
   "__set__":true,
   "elements":[
    "cryptography",
    "django",
    "djangorestframework",
    "pyjwt",
    "python",
    "requests"
   ]
  },
  "test":{
   "__set__":true,
   "elements":[]
  }
 },
 "meta_yaml":{
  "about":{
   "home":"https://github.com/labd/django-cognito-jwt",
   "license":"MIT",
   "license_family":"MIT",
   "license_file":"LICENSE",
   "summary":"An Authentication backend for Django Rest Framework for AWS Cognito JWT tokens"
  },
  "build":{
   "noarch":"python",
   "number":"0",
   "script":" -m pip install . -vv"
  },
  "extra":{
   "recipe-maintainers":[
    "hadim",
    "hadim",
    "hadim"
   ]
  },
  "package":{
   "name":"django-cognito-jwt",
   "version":"0.0.3"
  },
  "requirements":{
   "host":[
    "python",
    "pip",
    "python",
    "pip",
    "python",
    "pip"
   ],
   "run":[
    "python",
    "django >=1.11",
    "cryptography",
    "djangorestframework",
    "pyjwt",
    "requests",
    "python",
    "django >=1.11",
    "cryptography",
    "djangorestframework",
    "pyjwt",
    "requests",
    "python",
    "django >=1.11",
    "cryptography",
    "djangorestframework",
    "pyjwt",
    "requests"
   ]
  },
  "source":{
   "sha256":"6e9dfb79b262c338a493b71f81811621f88fb0af88d4b86e896252a9c00c81bf",
   "url":"https://pypi.io/packages/source/d/django-cognito-jwt/django-cognito-jwt-0.0.3.tar.gz"
  },
  "test":{
   "imports":[
    "django_cognito_jwt",
    "django_cognito_jwt",
    "django_cognito_jwt"
   ]
  }
 },
 "name":"django-cognito-jwt",
 "new_version":"0.0.3",
 "osx_64_meta_yaml":{
  "about":{
   "home":"https://github.com/labd/django-cognito-jwt",
   "license":"MIT",
   "license_family":"MIT",
   "license_file":"LICENSE",
   "summary":"An Authentication backend for Django Rest Framework for AWS Cognito JWT tokens"
  },
  "build":{
   "noarch":"python",
   "number":"0",
   "script":" -m pip install . -vv"
  },
  "extra":{
   "recipe-maintainers":[
    "hadim"
   ]
  },
  "package":{
   "name":"django-cognito-jwt",
   "version":"0.0.3"
  },
  "requirements":{
   "host":[
    "python",
    "pip"
   ],
   "run":[
    "python",
    "django >=1.11",
    "cryptography",
    "djangorestframework",
    "pyjwt",
    "requests"
   ]
  },
  "source":{
   "sha256":"6e9dfb79b262c338a493b71f81811621f88fb0af88d4b86e896252a9c00c81bf",
   "url":"https://pypi.io/packages/source/d/django-cognito-jwt/django-cognito-jwt-0.0.3.tar.gz"
  },
  "test":{
   "imports":[
    "django_cognito_jwt"
   ]
  }
 },
 "osx_64_requirements":{
  "build":{
   "__set__":true,
   "elements":[]
  },
  "host":{
   "__set__":true,
   "elements":[
    "pip",
    "python"
   ]
  },
  "run":{
   "__set__":true,
   "elements":[
    "cryptography",
    "django",
    "djangorestframework",
    "pyjwt",
    "python",
    "requests"
   ]
  },
  "test":{
   "__set__":true,
   "elements":[]
  }
 },
 "raw_meta_yaml":"{% set name = \"django-cognito-jwt\" %}\n{% set version = \"0.0.3\" %}\n\npackage:\n  name: {{ name|lower }}\n  version: {{ version }}\n\nsource:\n  url: https://pypi.io/packages/source/{{ name[0] }}/{{ name }}/{{ name }}-{{ version }}.tar.gz\n  sha256: 6e9dfb79b262c338a493b71f81811621f88fb0af88d4b86e896252a9c00c81bf\n\nbuild:\n  noarch: python\n  number: 0\n  script: \"{{ PYTHON }} -m pip install . -vv\"\n\nrequirements:\n  host:\n    - python\n    - pip\n  run:\n    - python\n    - django >=1.11\n    - cryptography\n    - djangorestframework\n    - pyjwt\n    - requests\n\ntest:\n  imports:\n    - django_cognito_jwt\n\nabout:\n  home: https://github.com/labd/django-cognito-jwt\n  license: MIT\n  license_family: MIT\n  # https://github.com/labd/django-cognito-jwt/issues/31\n  license_file: LICENSE\n  summary: 'An Authentication backend for Django Rest Framework for AWS Cognito JWT tokens'\n\nextra:\n  recipe-maintainers:\n    - hadim\n",
 "req":{
  "__set__":true,
  "elements":[
   "cryptography",
   "django",
   "djangorestframework",
   "pip",
   "pyjwt",
   "python",
   "requests"
  ]
 },
 "requirements":{
  "build":{
   "__set__":true,
   "elements":[]
  },
  "host":{
   "__set__":true,
   "elements":[
    "pip",
    "python"
   ]
  },
  "run":{
   "__set__":true,
   "elements":[
    "cryptography",
    "django",
    "djangorestframework",
    "pyjwt",
    "python",
    "requests"
   ]
  },
  "test":{
   "__set__":true,
   "elements":[]
  }
 },
 "strong_exports":false,
 "total_requirements":{
  "build":{
   "__set__":true,
   "elements":[]
  },
  "host":{
   "__set__":true,
   "elements":[
    "pip",
    "python"
   ]
  },
  "run":{
   "__set__":true,
   "elements":[
    "cryptography",
    "django >=1.11",
    "djangorestframework",
    "pyjwt",
    "python",
    "requests"
   ]
  },
  "test":{
   "__set__":true,
   "elements":[]
  }
 },
 "url":"https://pypi.io/packages/source/d/django-cognito-jwt/django-cognito-jwt-0.0.3.tar.gz",
 "version":"0.0.3",
 "win_64_meta_yaml":{
  "about":{
   "home":"https://github.com/labd/django-cognito-jwt",
   "license":"MIT",
   "license_family":"MIT",
   "license_file":"LICENSE",
   "summary":"An Authentication backend for Django Rest Framework for AWS Cognito JWT tokens"
  },
  "build":{
   "noarch":"python",
   "number":"0",
   "script":" -m pip install . -vv"
  },
  "extra":{
   "recipe-maintainers":[
    "hadim"
   ]
  },
  "package":{
   "name":"django-cognito-jwt",
   "version":"0.0.3"
  },
  "requirements":{
   "host":[
    "python",
    "pip"
   ],
   "run":[
    "python",
    "django >=1.11",
    "cryptography",
    "djangorestframework",
    "pyjwt",
    "requests"
   ]
  },
  "source":{
   "sha256":"6e9dfb79b262c338a493b71f81811621f88fb0af88d4b86e896252a9c00c81bf",
   "url":"https://pypi.io/packages/source/d/django-cognito-jwt/django-cognito-jwt-0.0.3.tar.gz"
  },
  "test":{
   "imports":[
    "django_cognito_jwt"
   ]
  }
 },
 "win_64_requirements":{
  "build":{
   "__set__":true,
   "elements":[]
  },
  "host":{
   "__set__":true,
   "elements":[
    "pip",
    "python"
   ]
  },
  "run":{
   "__set__":true,
   "elements":[
    "cryptography",
    "django",
    "djangorestframework",
    "pyjwt",
    "python",
    "requests"
   ]
  },
  "test":{
   "__set__":true,
   "elements":[]
  }
 }
}