{
 "archived":false,
 "bad":false,
 "conda-forge.yml":{},
 "feedstock_name":"hunspell-en",
 "hash_type":"sha256",
 "linux_64_meta_yaml":{
  "about":{
   "home":"https://github.com/marcoagpinto/aoo-mozilla-en-dict",
   "license":"LGPL-3.0-or-later",
   "license_file":"README_en_GB.txt",
   "summary":"English Dictionaries Project (AOO+Mozilla+others)"
  },
  "build":{
   "noarch":"generic",
   "number":"0"
  },
  "extra":{
   "recipe-maintainers":[
    "scopatz",
    "bollwyvl"
   ]
  },
  "outputs":[
   {
    "build":{
     "noarch":"generic"
    },
    "name":"hunspell-en",
    "requirements":{
     "run":[
      "hunspell",
      "aoo-mozilla-en-dict-au",
      "aoo-mozilla-en-dict-ca",
      "aoo-mozilla-en-dict-gb",
      "aoo-mozilla-en-dict-us",
      "aoo-mozilla-en-dict-za"
     ]
    },
    "test":{
     "commands":[
      "cd  && python hunspell_test.py"
     ],
     "requires":[
      "hunspell",
      "python >=3.6"
     ]
    }
   },
   {
    "about":{
     "license":"MIT",
     "license_file":"README_en_AU.txt"
    },
    "build":{
     "noarch":"generic"
    },
    "name":"aoo-mozilla-en-dict-au",
    "script":"copy_files.py",
    "test":{
     "commands":[
      "cd  && python hunspell_test.py"
     ],
     "requires":[
      "hunspell",
      "python >=3.6"
     ]
    }
   },
   {
    "about":{
     "license":"MIT",
     "license_file":"README_en_CA.txt"
    },
    "build":{
     "noarch":"generic"
    },
    "name":"aoo-mozilla-en-dict-ca",
    "script":"copy_files.py",
    "test":{
     "commands":[
      "cd  && python hunspell_test.py"
     ],
     "requires":[
      "hunspell",
      "python >=3.6"
     ]
    }
   },
   {
    "about":{
     "license":"LGPL-3.0-or-later",
     "license_file":"README_en_GB.txt"
    },
    "build":{
     "noarch":"generic"
    },
    "name":"aoo-mozilla-en-dict-gb",
    "script":"copy_files.py",
    "test":{
     "commands":[
      "cd  && python hunspell_test.py"
     ],
     "requires":[
      "hunspell",
      "python >=3.6"
     ]
    }
   },
   {
    "about":{
     "license":"MIT",
     "license_file":"README_en_US.txt"
    },
    "build":{
     "noarch":"generic"
    },
    "name":"aoo-mozilla-en-dict-us",
    "script":"copy_files.py",
    "test":{
     "commands":[
      "cd  && python hunspell_test.py"
     ],
     "requires":[
      "hunspell",
      "python >=3.6"
     ]
    }
   },
   {
    "about":{
     "license":"LGPL-3.0-or-later",
     "license_file":"README_en_ZA.txt"
    },
    "build":{
     "noarch":"generic"
    },
    "name":"aoo-mozilla-en-dict-za",
    "script":"copy_files.py",
    "test":{
     "commands":[
      "cd  && python hunspell_test.py"
     ],
     "requires":[
      "hunspell",
      "python >=3.6"
     ]
    }
   }
  ],
  "package":{
   "name":"aoo-mozilla-en-dict",
   "version":"2020.06.01"
  },
  "requirements":{
   "build":[
    "python >=3.6"
   ]
  },
  "source":{
   "sha256":"02fca6f1d4218c37769fb10f87c30bc5e7cf49716fa07b592874a9ef1edb4f72",
   "url":"https://github.com/marcoagpinto/aoo-mozilla-en-dict/archive/2020-06-01gb.tar.gz"
  }
 },
 "linux_64_requirements":{
  "build":{
   "__set__":true,
   "elements":[
    "python"
   ]
  },
  "host":{
   "__set__":true,
   "elements":[]
  },
  "run":{
   "__set__":true,
   "elements":[
    "aoo-mozilla-en-dict-au",
    "aoo-mozilla-en-dict-ca",
    "aoo-mozilla-en-dict-gb",
    "aoo-mozilla-en-dict-us",
    "aoo-mozilla-en-dict-za",
    "hunspell"
   ]
  },
  "test":{
   "__set__":true,
   "elements":[
    "hunspell",
    "python"
   ]
  }
 },
 "meta_yaml":{
  "about":{
   "home":"https://github.com/marcoagpinto/aoo-mozilla-en-dict",
   "license":"LGPL-3.0-or-later",
   "license_file":"README_en_GB.txt",
   "summary":"English Dictionaries Project (AOO+Mozilla+others)"
  },
  "build":{
   "noarch":"generic",
   "number":"0"
  },
  "extra":{
   "recipe-maintainers":[
    "scopatz",
    "bollwyvl",
    "scopatz",
    "bollwyvl",
    "scopatz",
    "bollwyvl"
   ]
  },
  "outputs":[
   {
    "build":{
     "noarch":"generic"
    },
    "name":"hunspell-en",
    "requirements":{
     "run":[
      "hunspell",
      "aoo-mozilla-en-dict-au",
      "aoo-mozilla-en-dict-ca",
      "aoo-mozilla-en-dict-gb",
      "aoo-mozilla-en-dict-us",
      "aoo-mozilla-en-dict-za"
     ]
    },
    "test":{
     "commands":[
      "cd  && python hunspell_test.py"
     ],
     "requires":[
      "hunspell",
      "python >=3.6"
     ]
    }
   },
   {
    "about":{
     "license":"MIT",
     "license_file":"README_en_AU.txt"
    },
    "build":{
     "noarch":"generic"
    },
    "name":"aoo-mozilla-en-dict-au",
    "script":"copy_files.py",
    "test":{
     "commands":[
      "cd  && python hunspell_test.py"
     ],
     "requires":[
      "hunspell",
      "python >=3.6"
     ]
    }
   },
   {
    "about":{
     "license":"MIT",
     "license_file":"README_en_CA.txt"
    },
    "build":{
     "noarch":"generic"
    },
    "name":"aoo-mozilla-en-dict-ca",
    "script":"copy_files.py",
    "test":{
     "commands":[
      "cd  && python hunspell_test.py"
     ],
     "requires":[
      "hunspell",
      "python >=3.6"
     ]
    }
   },
   {
    "about":{
     "license":"LGPL-3.0-or-later",
     "license_file":"README_en_GB.txt"
    },
    "build":{
     "noarch":"generic"
    },
    "name":"aoo-mozilla-en-dict-gb",
    "script":"copy_files.py",
    "test":{
     "commands":[
      "cd  && python hunspell_test.py"
     ],
     "requires":[
      "hunspell",
      "python >=3.6"
     ]
    }
   },
   {
    "about":{
     "license":"MIT",
     "license_file":"README_en_US.txt"
    },
    "build":{
     "noarch":"generic"
    },
    "name":"aoo-mozilla-en-dict-us",
    "script":"copy_files.py",
    "test":{
     "commands":[
      "cd  && python hunspell_test.py"
     ],
     "requires":[
      "hunspell",
      "python >=3.6"
     ]
    }
   },
   {
    "about":{
     "license":"LGPL-3.0-or-later",
     "license_file":"README_en_ZA.txt"
    },
    "build":{
     "noarch":"generic"
    },
    "name":"aoo-mozilla-en-dict-za",
    "script":"copy_files.py",
    "test":{
     "commands":[
      "cd  && python hunspell_test.py"
     ],
     "requires":[
      "hunspell",
      "python >=3.6"
     ]
    }
   },
   {
    "build":{
     "noarch":"generic"
    },
    "name":"hunspell-en",
    "requirements":{
     "run":[
      "hunspell",
      "aoo-mozilla-en-dict-au",
      "aoo-mozilla-en-dict-ca",
      "aoo-mozilla-en-dict-gb",
      "aoo-mozilla-en-dict-us",
      "aoo-mozilla-en-dict-za"
     ]
    },
    "test":{
     "commands":[
      "cd  && python hunspell_test.py"
     ],
     "requires":[
      "hunspell",
      "python >=3.6"
     ]
    }
   },
   {
    "about":{
     "license":"MIT",
     "license_file":"README_en_AU.txt"
    },
    "build":{
     "noarch":"generic"
    },
    "name":"aoo-mozilla-en-dict-au",
    "script":"copy_files.py",
    "test":{
     "commands":[
      "cd  && python hunspell_test.py"
     ],
     "requires":[
      "hunspell",
      "python >=3.6"
     ]
    }
   },
   {
    "about":{
     "license":"MIT",
     "license_file":"README_en_CA.txt"
    },
    "build":{
     "noarch":"generic"
    },
    "name":"aoo-mozilla-en-dict-ca",
    "script":"copy_files.py",
    "test":{
     "commands":[
      "cd  && python hunspell_test.py"
     ],
     "requires":[
      "hunspell",
      "python >=3.6"
     ]
    }
   },
   {
    "about":{
     "license":"LGPL-3.0-or-later",
     "license_file":"README_en_GB.txt"
    },
    "build":{
     "noarch":"generic"
    },
    "name":"aoo-mozilla-en-dict-gb",
    "script":"copy_files.py",
    "test":{
     "commands":[
      "cd  && python hunspell_test.py"
     ],
     "requires":[
      "hunspell",
      "python >=3.6"
     ]
    }
   },
   {
    "about":{
     "license":"MIT",
     "license_file":"README_en_US.txt"
    },
    "build":{
     "noarch":"generic"
    },
    "name":"aoo-mozilla-en-dict-us",
    "script":"copy_files.py",
    "test":{
     "commands":[
      "cd  && python hunspell_test.py"
     ],
     "requires":[
      "hunspell",
      "python >=3.6"
     ]
    }
   },
   {
    "about":{
     "license":"LGPL-3.0-or-later",
     "license_file":"README_en_ZA.txt"
    },
    "build":{
     "noarch":"generic"
    },
    "name":"aoo-mozilla-en-dict-za",
    "script":"copy_files.py",
    "test":{
     "commands":[
      "cd  && python hunspell_test.py"
     ],
     "requires":[
      "hunspell",
      "python >=3.6"
     ]
    }
   },
   {
    "build":{
     "noarch":"generic"
    },
    "name":"hunspell-en",
    "requirements":{
     "run":[
      "hunspell",
      "aoo-mozilla-en-dict-au",
      "aoo-mozilla-en-dict-ca",
      "aoo-mozilla-en-dict-gb",
      "aoo-mozilla-en-dict-us",
      "aoo-mozilla-en-dict-za"
     ]
    },
    "test":{
     "commands":[
      "cd  && python hunspell_test.py"
     ],
     "requires":[
      "hunspell",
      "python >=3.6"
     ]
    }
   },
   {
    "about":{
     "license":"MIT",
     "license_file":"README_en_AU.txt"
    },
    "build":{
     "noarch":"generic"
    },
    "name":"aoo-mozilla-en-dict-au",
    "script":"copy_files.py",
    "test":{
     "commands":[
      "cd  && python hunspell_test.py"
     ],
     "requires":[
      "hunspell",
      "python >=3.6"
     ]
    }
   },
   {
    "about":{
     "license":"MIT",
     "license_file":"README_en_CA.txt"
    },
    "build":{
     "noarch":"generic"
    },
    "name":"aoo-mozilla-en-dict-ca",
    "script":"copy_files.py",
    "test":{
     "commands":[
      "cd  && python hunspell_test.py"
     ],
     "requires":[
      "hunspell",
      "python >=3.6"
     ]
    }
   },
   {
    "about":{
     "license":"LGPL-3.0-or-later",
     "license_file":"README_en_GB.txt"
    },
    "build":{
     "noarch":"generic"
    },
    "name":"aoo-mozilla-en-dict-gb",
    "script":"copy_files.py",
    "test":{
     "commands":[
      "cd  && python hunspell_test.py"
     ],
     "requires":[
      "hunspell",
      "python >=3.6"
     ]
    }
   },
   {
    "about":{
     "license":"MIT",
     "license_file":"README_en_US.txt"
    },
    "build":{
     "noarch":"generic"
    },
    "name":"aoo-mozilla-en-dict-us",
    "script":"copy_files.py",
    "test":{
     "commands":[
      "cd  && python hunspell_test.py"
     ],
     "requires":[
      "hunspell",
      "python >=3.6"
     ]
    }
   },
   {
    "about":{
     "license":"LGPL-3.0-or-later",
     "license_file":"README_en_ZA.txt"
    },
    "build":{
     "noarch":"generic"
    },
    "name":"aoo-mozilla-en-dict-za",
    "script":"copy_files.py",
    "test":{
     "commands":[
      "cd  && python hunspell_test.py"
     ],
     "requires":[
      "hunspell",
      "python >=3.6"
     ]
    }
   }
  ],
  "package":{
   "name":"aoo-mozilla-en-dict",
   "version":"2020.06.01"
  },
  "requirements":{
   "build":[
    "python >=3.6",
    "python >=3.6",
    "python >=3.6"
   ]
  },
  "source":{
   "sha256":"02fca6f1d4218c37769fb10f87c30bc5e7cf49716fa07b592874a9ef1edb4f72",
   "url":"https://github.com/marcoagpinto/aoo-mozilla-en-dict/archive/2020-06-01gb.tar.gz"
  }
 },
 "name":"aoo-mozilla-en-dict",
 "new_version":false,
 "osx_64_meta_yaml":{
  "about":{
   "home":"https://github.com/marcoagpinto/aoo-mozilla-en-dict",
   "license":"LGPL-3.0-or-later",
   "license_file":"README_en_GB.txt",
   "summary":"English Dictionaries Project (AOO+Mozilla+others)"
  },
  "build":{
   "noarch":"generic",
   "number":"0"
  },
  "extra":{
   "recipe-maintainers":[
    "scopatz",
    "bollwyvl"
   ]
  },
  "outputs":[
   {
    "build":{
     "noarch":"generic"
    },
    "name":"hunspell-en",
    "requirements":{
     "run":[
      "hunspell",
      "aoo-mozilla-en-dict-au",
      "aoo-mozilla-en-dict-ca",
      "aoo-mozilla-en-dict-gb",
      "aoo-mozilla-en-dict-us",
      "aoo-mozilla-en-dict-za"
     ]
    },
    "test":{
     "commands":[
      "cd  && python hunspell_test.py"
     ],
     "requires":[
      "hunspell",
      "python >=3.6"
     ]
    }
   },
   {
    "about":{
     "license":"MIT",
     "license_file":"README_en_AU.txt"
    },
    "build":{
     "noarch":"generic"
    },
    "name":"aoo-mozilla-en-dict-au",
    "script":"copy_files.py",
    "test":{
     "commands":[
      "cd  && python hunspell_test.py"
     ],
     "requires":[
      "hunspell",
      "python >=3.6"
     ]
    }
   },
   {
    "about":{
     "license":"MIT",
     "license_file":"README_en_CA.txt"
    },
    "build":{
     "noarch":"generic"
    },
    "name":"aoo-mozilla-en-dict-ca",
    "script":"copy_files.py",
    "test":{
     "commands":[
      "cd  && python hunspell_test.py"
     ],
     "requires":[
      "hunspell",
      "python >=3.6"
     ]
    }
   },
   {
    "about":{
     "license":"LGPL-3.0-or-later",
     "license_file":"README_en_GB.txt"
    },
    "build":{
     "noarch":"generic"
    },
    "name":"aoo-mozilla-en-dict-gb",
    "script":"copy_files.py",
    "test":{
     "commands":[
      "cd  && python hunspell_test.py"
     ],
     "requires":[
      "hunspell",
      "python >=3.6"
     ]
    }
   },
   {
    "about":{
     "license":"MIT",
     "license_file":"README_en_US.txt"
    },
    "build":{
     "noarch":"generic"
    },
    "name":"aoo-mozilla-en-dict-us",
    "script":"copy_files.py",
    "test":{
     "commands":[
      "cd  && python hunspell_test.py"
     ],
     "requires":[
      "hunspell",
      "python >=3.6"
     ]
    }
   },
   {
    "about":{
     "license":"LGPL-3.0-or-later",
     "license_file":"README_en_ZA.txt"
    },
    "build":{
     "noarch":"generic"
    },
    "name":"aoo-mozilla-en-dict-za",
    "script":"copy_files.py",
    "test":{
     "commands":[
      "cd  && python hunspell_test.py"
     ],
     "requires":[
      "hunspell",
      "python >=3.6"
     ]
    }
   }
  ],
  "package":{
   "name":"aoo-mozilla-en-dict",
   "version":"2020.06.01"
  },
  "requirements":{
   "build":[
    "python >=3.6"
   ]
  },
  "source":{
   "sha256":"02fca6f1d4218c37769fb10f87c30bc5e7cf49716fa07b592874a9ef1edb4f72",
   "url":"https://github.com/marcoagpinto/aoo-mozilla-en-dict/archive/2020-06-01gb.tar.gz"
  }
 },
 "osx_64_requirements":{
  "build":{
   "__set__":true,
   "elements":[
    "python"
   ]
  },
  "host":{
   "__set__":true,
   "elements":[]
  },
  "run":{
   "__set__":true,
   "elements":[
    "aoo-mozilla-en-dict-au",
    "aoo-mozilla-en-dict-ca",
    "aoo-mozilla-en-dict-gb",
    "aoo-mozilla-en-dict-us",
    "aoo-mozilla-en-dict-za",
    "hunspell"
   ]
  },
  "test":{
   "__set__":true,
   "elements":[
    "hunspell",
    "python"
   ]
  }
 },
 "outputs_names":[
  "aoo-mozilla-en-dict-au",
  "aoo-mozilla-en-dict-ca",
  "aoo-mozilla-en-dict-gb",
  "aoo-mozilla-en-dict-us",
  "aoo-mozilla-en-dict-za",
  "hunspell-en"
 ],
 "raw_meta_yaml":"{% set name = \"aoo-mozilla-en-dict\" %}\n{% set version = \"2020-06-01\" %}\n\npackage:\n  name: {{ name }}\n  version: {{ version.replace(\"-\", \".\") }}\n\nsource:\n  url: https://github.com/marcoagpinto/{{ name }}/archive/{{ version }}gb.tar.gz\n  sha256: 02fca6f1d4218c37769fb10f87c30bc5e7cf49716fa07b592874a9ef1edb4f72\n\nbuild:\n  number: 0\n  noarch: generic\n\nrequirements:\n  build:\n    - python >=3.6\n\noutputs:\n  - name: hunspell-en\n    build:\n      noarch: generic\n    requirements:\n      run:\n        - hunspell\n        - {{ name }}-au\n        - {{ name }}-ca\n        - {{ name }}-gb\n        - {{ name }}-us\n        - {{ name }}-za\n    test:\n      requires:\n        - hunspell\n        - python >=3.6\n      commands:\n        - cd {{ RECIPE_DIR }} && python hunspell_test.py\n\n  - name: {{ name }}-au\n    build:\n      noarch: generic\n    script: copy_files.py\n    about:\n      license: MIT\n      license_file: README_en_AU.txt\n    test:\n      requires:\n        - hunspell\n        - python >=3.6\n      commands:\n        - cd {{ RECIPE_DIR }} && python hunspell_test.py\n\n  - name: {{ name }}-ca\n    build:\n      noarch: generic\n    script: copy_files.py\n    about:\n      license: MIT\n      license_file: README_en_CA.txt\n    test:\n      requires:\n        - hunspell\n        - python >=3.6\n      commands:\n        - cd {{ RECIPE_DIR }} && python hunspell_test.py\n\n  - name: {{ name }}-gb\n    build:\n      noarch: generic\n    script: copy_files.py\n    about:\n      license: LGPL-3.0-or-later\n      license_file: README_en_GB.txt\n    test:\n      requires:\n        - hunspell\n        - python >=3.6\n      commands:\n        - cd {{ RECIPE_DIR }} && python hunspell_test.py\n\n  - name: {{ name }}-us\n    build:\n      noarch: generic\n    script: copy_files.py\n    about:\n      license: MIT\n      license_file: README_en_US.txt\n    test:\n      requires:\n        - hunspell\n        - python >=3.6\n      commands:\n        - cd {{ RECIPE_DIR }} && python hunspell_test.py\n\n  - name: {{ name }}-za\n    build:\n      noarch: generic\n    script: copy_files.py\n    about:\n      license: LGPL-3.0-or-later\n      license_file: README_en_ZA.txt\n    test:\n      requires:\n        - hunspell\n        - python >=3.6\n      commands:\n        - cd {{ RECIPE_DIR }} && python hunspell_test.py\n\nabout:\n  home: https://github.com/marcoagpinto/aoo-mozilla-en-dict\n  summary: 'English Dictionaries Project (AOO+Mozilla+others)'\n  license: LGPL-3.0-or-later\n  license_file: README_en_GB.txt\n\nextra:\n  recipe-maintainers:\n    - scopatz\n    - bollwyvl\n",
 "req":{
  "__set__":true,
  "elements":[
   "aoo-mozilla-en-dict-au",
   "aoo-mozilla-en-dict-ca",
   "aoo-mozilla-en-dict-gb",
   "aoo-mozilla-en-dict-us",
   "aoo-mozilla-en-dict-za",
   "hunspell",
   "python"
  ]
 },
 "requirements":{
  "build":{
   "__set__":true,
   "elements":[
    "python"
   ]
  },
  "host":{
   "__set__":true,
   "elements":[]
  },
  "run":{
   "__set__":true,
   "elements":[
    "aoo-mozilla-en-dict-au",
    "aoo-mozilla-en-dict-ca",
    "aoo-mozilla-en-dict-gb",
    "aoo-mozilla-en-dict-us",
    "aoo-mozilla-en-dict-za",
    "hunspell"
   ]
  },
  "test":{
   "__set__":true,
   "elements":[
    "hunspell",
    "python"
   ]
  }
 },
 "strong_exports":false,
 "total_requirements":{
  "build":{
   "__set__":true,
   "elements":[
    "python >=3.6"
   ]
  },
  "host":{
   "__set__":true,
   "elements":[]
  },
  "run":{
   "__set__":true,
   "elements":[
    "aoo-mozilla-en-dict-au",
    "aoo-mozilla-en-dict-ca",
    "aoo-mozilla-en-dict-gb",
    "aoo-mozilla-en-dict-us",
    "aoo-mozilla-en-dict-za",
    "hunspell"
   ]
  },
  "test":{
   "__set__":true,
   "elements":[
    "hunspell",
    "python >=3.6"
   ]
  }
 },
 "url":"https://extensions.openoffice.org/en/download/18746",
 "version":"2020.06.01",
 "win_64_meta_yaml":{
  "about":{
   "home":"https://github.com/marcoagpinto/aoo-mozilla-en-dict",
   "license":"LGPL-3.0-or-later",
   "license_file":"README_en_GB.txt",
   "summary":"English Dictionaries Project (AOO+Mozilla+others)"
  },
  "build":{
   "noarch":"generic",
   "number":"0"
  },
  "extra":{
   "recipe-maintainers":[
    "scopatz",
    "bollwyvl"
   ]
  },
  "outputs":[
   {
    "build":{
     "noarch":"generic"
    },
    "name":"hunspell-en",
    "requirements":{
     "run":[
      "hunspell",
      "aoo-mozilla-en-dict-au",
      "aoo-mozilla-en-dict-ca",
      "aoo-mozilla-en-dict-gb",
      "aoo-mozilla-en-dict-us",
      "aoo-mozilla-en-dict-za"
     ]
    },
    "test":{
     "commands":[
      "cd  && python hunspell_test.py"
     ],
     "requires":[
      "hunspell",
      "python >=3.6"
     ]
    }
   },
   {
    "about":{
     "license":"MIT",
     "license_file":"README_en_AU.txt"
    },
    "build":{
     "noarch":"generic"
    },
    "name":"aoo-mozilla-en-dict-au",
    "script":"copy_files.py",
    "test":{
     "commands":[
      "cd  && python hunspell_test.py"
     ],
     "requires":[
      "hunspell",
      "python >=3.6"
     ]
    }
   },
   {
    "about":{
     "license":"MIT",
     "license_file":"README_en_CA.txt"
    },
    "build":{
     "noarch":"generic"
    },
    "name":"aoo-mozilla-en-dict-ca",
    "script":"copy_files.py",
    "test":{
     "commands":[
      "cd  && python hunspell_test.py"
     ],
     "requires":[
      "hunspell",
      "python >=3.6"
     ]
    }
   },
   {
    "about":{
     "license":"LGPL-3.0-or-later",
     "license_file":"README_en_GB.txt"
    },
    "build":{
     "noarch":"generic"
    },
    "name":"aoo-mozilla-en-dict-gb",
    "script":"copy_files.py",
    "test":{
     "commands":[
      "cd  && python hunspell_test.py"
     ],
     "requires":[
      "hunspell",
      "python >=3.6"
     ]
    }
   },
   {
    "about":{
     "license":"MIT",
     "license_file":"README_en_US.txt"
    },
    "build":{
     "noarch":"generic"
    },
    "name":"aoo-mozilla-en-dict-us",
    "script":"copy_files.py",
    "test":{
     "commands":[
      "cd  && python hunspell_test.py"
     ],
     "requires":[
      "hunspell",
      "python >=3.6"
     ]
    }
   },
   {
    "about":{
     "license":"LGPL-3.0-or-later",
     "license_file":"README_en_ZA.txt"
    },
    "build":{
     "noarch":"generic"
    },
    "name":"aoo-mozilla-en-dict-za",
    "script":"copy_files.py",
    "test":{
     "commands":[
      "cd  && python hunspell_test.py"
     ],
     "requires":[
      "hunspell",
      "python >=3.6"
     ]
    }
   }
  ],
  "package":{
   "name":"aoo-mozilla-en-dict",
   "version":"2020.06.01"
  },
  "requirements":{
   "build":[
    "python >=3.6"
   ]
  },
  "source":{
   "sha256":"02fca6f1d4218c37769fb10f87c30bc5e7cf49716fa07b592874a9ef1edb4f72",
   "url":"https://github.com/marcoagpinto/aoo-mozilla-en-dict/archive/2020-06-01gb.tar.gz"
  }
 },
 "win_64_requirements":{
  "build":{
   "__set__":true,
   "elements":[
    "python"
   ]
  },
  "host":{
   "__set__":true,
   "elements":[]
  },
  "run":{
   "__set__":true,
   "elements":[
    "aoo-mozilla-en-dict-au",
    "aoo-mozilla-en-dict-ca",
    "aoo-mozilla-en-dict-gb",
    "aoo-mozilla-en-dict-us",
    "aoo-mozilla-en-dict-za",
    "hunspell"
   ]
  },
  "test":{
   "__set__":true,
   "elements":[
    "hunspell",
    "python"
   ]
  }
 }
}