{
 "PRed":[
  {
   "data":{
    "bot_rerun":false,
    "migrator_name":"Version",
    "migrator_version":0,
    "version":"0.19"
   },
   "keys":[
    "bot_rerun",
    "migrator_name",
    "migrator_version",
    "version"
   ]
  },
  {
   "PR":{
    "__lazy_json__":"pr_json/204613130.json"
   },
   "data":{
    "bot_rerun":false,
    "migrator_name":"Version",
    "migrator_version":0,
    "version":"0.20"
   },
   "keys":[
    "bot_rerun",
    "migrator_name",
    "migrator_version",
    "version"
   ]
  },
  {
   "PR":{
    "__lazy_json__":"pr_json/215802051.json"
   },
   "data":{
    "bot_rerun":false,
    "migrator_name":"CompilerRebuild",
    "migrator_version":1,
    "name":"Python 3.7, GCC 7, R 3.5.1, openBLAS 0.3.2"
   },
   "keys":[
    "bot_rerun",
    "migrator_name",
    "migrator_version",
    "name"
   ]
  },
  {
   "PR":{
    "__lazy_json__":"pr_json/264681549.json"
   },
   "data":{
    "bot_rerun":false,
    "migrator_name":"Version",
    "migrator_version":0,
    "version":"0.21"
   },
   "keys":[
    "bot_rerun",
    "migrator_name",
    "migrator_version",
    "version"
   ]
  },
  {
   "PR":{
    "__lazy_json__":"pr_json/338977218.json"
   },
   "data":{
    "bot_rerun":1593642863.059089,
    "migrator_name":"Version",
    "migrator_version":0,
    "version":"0.22"
   },
   "keys":[
    "bot_rerun",
    "migrator_name",
    "migrator_version",
    "version"
   ]
  },
  {
   "PR":{
    "__lazy_json__":"pr_json/429396781.json"
   },
   "data":{
    "bot_rerun":false,
    "migrator_name":"ArchRebuild",
    "migrator_version":1,
    "name":"aarch64 and ppc64le addition"
   },
   "keys":[
    "bot_rerun",
    "migrator_name",
    "migrator_version",
    "name"
   ]
  },
  {
   "PR":{
    "__lazy_json__":"pr_json/443036890.json"
   },
   "data":{
    "bot_rerun":false,
    "migrator_name":"Version",
    "migrator_version":0,
    "version":"0.22"
   },
   "keys":[
    "bot_rerun",
    "migrator_name",
    "migrator_version",
    "version"
   ]
  }
 ],
 "archived":false,
 "bad":"Upstream: unknown source",
 "conda-forge.yml":{
  "provider":{
   "linux_aarch64":"default",
   "linux_ppc64le":"default"
  }
 },
 "feedstock_name":"isl",
 "hash_type":"sha256",
 "linux_64_meta_yaml":{
  "about":{
   "home":"http://isl.gforge.inria.fr/",
   "license":"MIT",
   "license_family":"MIT",
   "license_file":"LICENSE",
   "summary":"a thread-safe C library for manipulating sets and relations of integer points bounded by affine constraints."
  },
  "build":{
   "number":"1",
   "run_exports":[
    "isl"
   ]
  },
  "extra":{
   "recipe-maintainers":[
    "frol",
    "isuruf"
   ]
  },
  "package":{
   "name":"isl",
   "version":"0.22.1"
  },
  "requirements":{
   "build":[
    "c_compiler_stub",
    "make"
   ],
   "host":[
    "gmp"
   ],
   "run":[
    "gmp"
   ]
  },
  "source":{
   "fn":"isl-0.22.1.tar.bz2",
   "patches":null,
   "sha256":"1a668ef92eb181a7c021e8531a3ca89fd71aa1b3744db56f68365ab0a224c5cd",
   "url":"http://isl.gforge.inria.fr/isl-0.22.1.tar.bz2"
  },
  "test":{
   "commands":[
    "test ! -f \"$PREFIX/lib/libisl.a\"",
    "test -f \"$PREFIX/lib/libisl${SHLIB_EXT}\"",
    "test -d \"$PREFIX/include/isl\""
   ]
  }
 },
 "linux_64_requirements":{
  "build":{
   "__set__":true,
   "elements":[
    "c_compiler_stub",
    "make"
   ]
  },
  "host":{
   "__set__":true,
   "elements":[
    "gmp"
   ]
  },
  "run":{
   "__set__":true,
   "elements":[
    "gmp"
   ]
  },
  "test":{
   "__set__":true,
   "elements":[]
  }
 },
 "linux_aarch64_meta_yaml":{
  "about":{
   "home":"http://isl.gforge.inria.fr/",
   "license":"MIT",
   "license_family":"MIT",
   "license_file":"LICENSE",
   "summary":"a thread-safe C library for manipulating sets and relations of integer points bounded by affine constraints."
  },
  "build":{
   "number":"1",
   "run_exports":[
    "isl"
   ]
  },
  "extra":{
   "recipe-maintainers":[
    "frol",
    "isuruf"
   ]
  },
  "package":{
   "name":"isl",
   "version":"0.22.1"
  },
  "requirements":{
   "build":[
    "c_compiler_stub",
    "make"
   ],
   "host":[
    "gmp"
   ],
   "run":[
    "gmp"
   ]
  },
  "source":{
   "fn":"isl-0.22.1.tar.bz2",
   "patches":null,
   "sha256":"1a668ef92eb181a7c021e8531a3ca89fd71aa1b3744db56f68365ab0a224c5cd",
   "url":"http://isl.gforge.inria.fr/isl-0.22.1.tar.bz2"
  },
  "test":{
   "commands":[
    "test ! -f \"$PREFIX/lib/libisl.a\"",
    "test -f \"$PREFIX/lib/libisl${SHLIB_EXT}\"",
    "test -d \"$PREFIX/include/isl\""
   ]
  }
 },
 "linux_aarch64_requirements":{
  "build":{
   "__set__":true,
   "elements":[
    "c_compiler_stub",
    "make"
   ]
  },
  "host":{
   "__set__":true,
   "elements":[
    "gmp"
   ]
  },
  "run":{
   "__set__":true,
   "elements":[
    "gmp"
   ]
  },
  "test":{
   "__set__":true,
   "elements":[]
  }
 },
 "linux_ppc64le_meta_yaml":{
  "about":{
   "home":"http://isl.gforge.inria.fr/",
   "license":"MIT",
   "license_family":"MIT",
   "license_file":"LICENSE",
   "summary":"a thread-safe C library for manipulating sets and relations of integer points bounded by affine constraints."
  },
  "build":{
   "number":"1",
   "run_exports":[
    "isl"
   ]
  },
  "extra":{
   "recipe-maintainers":[
    "frol",
    "isuruf"
   ]
  },
  "package":{
   "name":"isl",
   "version":"0.22.1"
  },
  "requirements":{
   "build":[
    "c_compiler_stub",
    "make"
   ],
   "host":[
    "gmp"
   ],
   "run":[
    "gmp"
   ]
  },
  "source":{
   "fn":"isl-0.22.1.tar.bz2",
   "patches":null,
   "sha256":"1a668ef92eb181a7c021e8531a3ca89fd71aa1b3744db56f68365ab0a224c5cd",
   "url":"http://isl.gforge.inria.fr/isl-0.22.1.tar.bz2"
  },
  "test":{
   "commands":[
    "test ! -f \"$PREFIX/lib/libisl.a\"",
    "test -f \"$PREFIX/lib/libisl${SHLIB_EXT}\"",
    "test -d \"$PREFIX/include/isl\""
   ]
  }
 },
 "linux_ppc64le_requirements":{
  "build":{
   "__set__":true,
   "elements":[
    "c_compiler_stub",
    "make"
   ]
  },
  "host":{
   "__set__":true,
   "elements":[
    "gmp"
   ]
  },
  "run":{
   "__set__":true,
   "elements":[
    "gmp"
   ]
  },
  "test":{
   "__set__":true,
   "elements":[]
  }
 },
 "meta_yaml":{
  "about":{
   "home":"http://isl.gforge.inria.fr/",
   "license":"MIT",
   "license_family":"MIT",
   "license_file":"LICENSE",
   "summary":"a thread-safe C library for manipulating sets and relations of integer points bounded by affine constraints."
  },
  "build":{
   "number":"1",
   "run_exports":[
    "isl",
    "isl",
    "isl",
    "isl",
    "isl"
   ]
  },
  "extra":{
   "recipe-maintainers":[
    "frol",
    "isuruf",
    "frol",
    "isuruf",
    "frol",
    "isuruf",
    "frol",
    "isuruf",
    "frol",
    "isuruf"
   ]
  },
  "package":{
   "name":"isl",
   "version":"0.22.1"
  },
  "requirements":{
   "build":[
    "c_compiler_stub",
    "autotools_clang_conda",
    "c_compiler_stub",
    "make",
    "c_compiler_stub",
    "make",
    "c_compiler_stub",
    "make",
    "c_compiler_stub",
    "make"
   ],
   "host":[
    "gmp"
   ],
   "run":[
    "gmp"
   ]
  },
  "source":{
   "fn":"isl-0.22.1.tar.bz2",
   "patches":null,
   "sha256":"1a668ef92eb181a7c021e8531a3ca89fd71aa1b3744db56f68365ab0a224c5cd",
   "url":"http://isl.gforge.inria.fr/isl-0.22.1.tar.bz2"
  },
  "test":{
   "commands":[
    "if not exist %LIBRARY_LIB%\\\\isl.lib exit 1",
    "if not exist %LIBRARY_INC%\\\\isl\\\\options.h exit 1",
    "test ! -f \"$PREFIX/lib/libisl.a\"",
    "test -f \"$PREFIX/lib/libisl${SHLIB_EXT}\"",
    "test -d \"$PREFIX/include/isl\"",
    "test ! -f \"$PREFIX/lib/libisl.a\"",
    "test -f \"$PREFIX/lib/libisl${SHLIB_EXT}\"",
    "test -d \"$PREFIX/include/isl\"",
    "test ! -f \"$PREFIX/lib/libisl.a\"",
    "test -f \"$PREFIX/lib/libisl${SHLIB_EXT}\"",
    "test -d \"$PREFIX/include/isl\"",
    "test ! -f \"$PREFIX/lib/libisl.a\"",
    "test -f \"$PREFIX/lib/libisl${SHLIB_EXT}\"",
    "test -d \"$PREFIX/include/isl\""
   ]
  }
 },
 "name":"isl",
 "new_version":false,
 "new_version_attempts":{
  "0.22":1
 },
 "new_version_errors":{},
 "osx_64_meta_yaml":{
  "about":{
   "home":"http://isl.gforge.inria.fr/",
   "license":"MIT",
   "license_family":"MIT",
   "license_file":"LICENSE",
   "summary":"a thread-safe C library for manipulating sets and relations of integer points bounded by affine constraints."
  },
  "build":{
   "number":"1",
   "run_exports":[
    "isl"
   ]
  },
  "extra":{
   "recipe-maintainers":[
    "frol",
    "isuruf"
   ]
  },
  "package":{
   "name":"isl",
   "version":"0.22.1"
  },
  "requirements":{
   "build":[
    "c_compiler_stub",
    "make"
   ],
   "host":[
    "gmp"
   ],
   "run":[
    "gmp"
   ]
  },
  "source":{
   "fn":"isl-0.22.1.tar.bz2",
   "patches":null,
   "sha256":"1a668ef92eb181a7c021e8531a3ca89fd71aa1b3744db56f68365ab0a224c5cd",
   "url":"http://isl.gforge.inria.fr/isl-0.22.1.tar.bz2"
  },
  "test":{
   "commands":[
    "test ! -f \"$PREFIX/lib/libisl.a\"",
    "test -f \"$PREFIX/lib/libisl${SHLIB_EXT}\"",
    "test -d \"$PREFIX/include/isl\""
   ]
  }
 },
 "osx_64_requirements":{
  "build":{
   "__set__":true,
   "elements":[
    "c_compiler_stub",
    "make"
   ]
  },
  "host":{
   "__set__":true,
   "elements":[
    "gmp"
   ]
  },
  "run":{
   "__set__":true,
   "elements":[
    "gmp"
   ]
  },
  "test":{
   "__set__":true,
   "elements":[]
  }
 },
 "pinning_version":"2020.07.01.21.17.12",
 "raw_meta_yaml":"{% set version = \"0.22.1\" %}\n\npackage:\n  name: isl\n  version: {{ version }}\n\nsource:\n  fn: isl-{{ version }}.tar.bz2\n  url: http://isl.gforge.inria.fr/isl-{{ version }}.tar.bz2\n  sha256: 1a668ef92eb181a7c021e8531a3ca89fd71aa1b3744db56f68365ab0a224c5cd\n  patches:\n    # From https://github.com/msys2/MINGW-packages/blob/master/mingw-w64-isl/isl-0.14.1-no-undefined.patch\n    - no_undefined.patch  # [win]\n\nbuild:\n  number: 1\n  run_exports:\n    - {{ pin_subpackage(\"isl\", max_pin=\"x.x\") }}\n\nrequirements:\n  build:\n    - {{ compiler('c') }}\n    - autotools_clang_conda  # [win]\n    - make                   # [unix]\n  host:\n    - gmp             # [unix]\n  run:\n    - gmp             # [unix]\n\ntest:\n  commands:\n    - if not exist %LIBRARY_LIB%\\\\isl.lib exit 1            # [win]\n    - if not exist %LIBRARY_INC%\\\\isl\\\\options.h exit 1     # [win]\n    - test ! -f \"$PREFIX/lib/libisl.a\"          # [unix]\n    - test -f \"$PREFIX/lib/libisl${SHLIB_EXT}\"  # [unix]\n    - test -d \"$PREFIX/include/isl\"             # [unix]\n\nabout:\n  home: http://isl.gforge.inria.fr/\n  license: MIT\n  license_family: MIT\n  license_file: LICENSE\n  summary: a thread-safe C library for manipulating sets and relations of integer points bounded by affine constraints.\n\nextra:\n  recipe-maintainers:\n    - frol\n    - isuruf\n",
 "req":{
  "__set__":true,
  "elements":[
   "autotools_clang_conda",
   "c_compiler_stub",
   "gmp",
   "make"
  ]
 },
 "requirements":{
  "build":{
   "__set__":true,
   "elements":[
    "autotools_clang_conda",
    "c_compiler_stub",
    "make"
   ]
  },
  "host":{
   "__set__":true,
   "elements":[
    "gmp"
   ]
  },
  "run":{
   "__set__":true,
   "elements":[
    "gmp"
   ]
  },
  "test":{
   "__set__":true,
   "elements":[]
  }
 },
 "smithy_version":"No azure token. Create a token and\nput it in ~/.conda-smithy/azure.token\n3.7.3\n",
 "strong_exports":false,
 "total_requirements":{
  "build":{
   "__set__":true,
   "elements":[
    "autotools_clang_conda",
    "c_compiler_stub",
    "make"
   ]
  },
  "host":{
   "__set__":true,
   "elements":[
    "gmp"
   ]
  },
  "run":{
   "__set__":true,
   "elements":[
    "gmp"
   ]
  },
  "test":{
   "__set__":true,
   "elements":[]
  }
 },
 "url":"http://isl.gforge.inria.fr/isl-0.21.tar.bz2",
 "version":"0.22.1",
 "win_64_meta_yaml":{
  "about":{
   "home":"http://isl.gforge.inria.fr/",
   "license":"MIT",
   "license_family":"MIT",
   "license_file":"LICENSE",
   "summary":"a thread-safe C library for manipulating sets and relations of integer points bounded by affine constraints."
  },
  "build":{
   "number":"1",
   "run_exports":[
    "isl"
   ]
  },
  "extra":{
   "recipe-maintainers":[
    "frol",
    "isuruf"
   ]
  },
  "package":{
   "name":"isl",
   "version":"0.22.1"
  },
  "requirements":{
   "build":[
    "c_compiler_stub",
    "autotools_clang_conda"
   ],
   "host":null,
   "run":null
  },
  "source":{
   "fn":"isl-0.22.1.tar.bz2",
   "patches":[
    "no_undefined.patch"
   ],
   "sha256":"1a668ef92eb181a7c021e8531a3ca89fd71aa1b3744db56f68365ab0a224c5cd",
   "url":"http://isl.gforge.inria.fr/isl-0.22.1.tar.bz2"
  },
  "test":{
   "commands":[
    "if not exist %LIBRARY_LIB%\\\\isl.lib exit 1",
    "if not exist %LIBRARY_INC%\\\\isl\\\\options.h exit 1"
   ]
  }
 },
 "win_64_requirements":{
  "build":{
   "__set__":true,
   "elements":[
    "autotools_clang_conda",
    "c_compiler_stub"
   ]
  },
  "host":{
   "__set__":true,
   "elements":[]
  },
  "run":{
   "__set__":true,
   "elements":[]
  },
  "test":{
   "__set__":true,
   "elements":[]
  }
 }
}