{
 "builtin":{
  "__set__":true,
  "elements":[
   "__future__",
   "collections",
   "distutils",
   "doctest",
   "functools",
   "itertools",
   "math",
   "multiprocessing",
   "os",
   "sys",
   "tempfile",
   "unittest",
   "warnings"
  ]
 },
 "questionable":{
  "__set__":true,
  "elements":[
   "esda",
   "geopandas",
   "joblib",
   "libpysal",
   "numba",
   "pandas",
   "scikit-learn"
  ]
 },
 "relative":{
  "__set__":true,
  "elements":[
   "crand",
   "gamma",
   "geary",
   "getisord",
   "join_counts",
   "lee",
   "moran",
   "silhouettes",
   "smaup",
   "smoothing",
   "tabular",
   "util"
  ]
 },
 "required":{
  "__set__":true,
  "elements":[
   "geopandas",
   "libpysal",
   "numpy",
   "pandas",
   "scikit-learn",
   "scipy",
   "setuptools"
  ]
 }
}