{
 "builtin":{
  "__set__":true,
  "elements":[
   "collections",
   "copy",
   "hashlib",
   "json",
   "logging",
   "math",
   "os",
   "pathlib",
   "shutil",
   "sys",
   "xml"
  ]
 },
 "questionable":{
  "__set__":true,
  "elements":[
   "uproot"
  ]
 },
 "relative":{
  "__set__":true,
  "elements":[
   "autodiff",
   "calculators",
   "cli",
   "code0",
   "code1",
   "code2",
   "code4",
   "code4p",
   "constraints",
   "exceptions",
   "histosys",
   "infer",
   "jax_backend",
   "lumi",
   "mixins",
   "mle",
   "normfactor",
   "normsys",
   "numpy_backend",
   "opt_jax",
   "opt_minuit",
   "opt_pytorch",
   "opt_scipy",
   "opt_tflow",
   "optimize",
   "parameters",
   "paramsets",
   "paramview",
   "patchset",
   "pdf",
   "pytorch_backend",
   "rootio",
   "shapefactor",
   "shapesys",
   "spec",
   "staterror",
   "tensor",
   "tensorflow_backend",
   "test_statistics",
   "utils",
   "version",
   "workspace"
  ]
 },
 "required":{
  "__set__":true,
  "elements":[
   "click",
   "iminuit",
   "jax",
   "jsonpatch",
   "jsonschema",
   "numpy",
   "pkg_resources",
   "pyyaml",
   "scipy",
   "setuptools",
   "tensorflow",
   "tensorflow_probability",
   "torch",
   "tqdm",
   "uproot",
   "uproot_methods"
  ]
 }
}