{
 "builtin":{
  "__set__":true,
  "elements":[
   "__future__",
   "argparse",
   "codecs",
   "distutils",
   "itertools",
   "math",
   "os",
   "subprocess",
   "sys",
   "tempfile"
  ]
 },
 "questionable":{
  "__set__":true,
  "elements":[
   "psutil"
  ]
 },
 "relative":{
  "__set__":true,
  "elements":[
   "rsync"
  ]
 },
 "required":{
  "__set__":true,
  "elements":[
   "execnet",
   "py",
   "pytest",
   "pytest_cloud",
   "setuptools",
   "six",
   "timeout_decorator",
   "xdist"
  ]
 }
}