{
 "builtin":{
  "__set__":true,
  "elements":[
   "__future__",
   "distutils",
   "glob",
   "inspect",
   "itertools",
   "os",
   "pydoc",
   "re",
   "sys",
   "tempfile",
   "textwrap"
  ]
 },
 "questionable":{
  "__set__":true,
  "elements":[
   "matplotlib",
   "networkx",
   "nose"
  ]
 },
 "relative":{
  "__set__":true,
  "elements":[
   "planarity",
   "planarity_functions",
   "planarity_networkx",
   "tests"
  ]
 },
 "required":{
  "__set__":true,
  "elements":[
   "Cython",
   "docscrape",
   "matplotlib",
   "networkx",
   "nose",
   "planarity",
   "setuptools",
   "sphinx"
  ]
 }
}