{
 "builtin":{
  "__set__":true,
  "elements":[
   "__future__",
   "configparser",
   "copy",
   "ctypes",
   "datetime",
   "distutils",
   "errno",
   "functools",
   "gc",
   "glob",
   "hashlib",
   "io",
   "itertools",
   "json",
   "os",
   "pickle",
   "platform",
   "pprint",
   "re",
   "shutil",
   "struct",
   "subprocess",
   "sys",
   "threading",
   "time",
   "warnings"
  ]
 },
 "questionable":{
  "__set__":true,
  "elements":[
   "ConfigParser",
   "Cython",
   "cffi",
   "cx_Freeze",
   "numba",
   "numpy",
   "py2exe",
   "pytest",
   "randomgen",
   "setuptools",
   "tempita"
  ]
 },
 "relative":{
  "__set__":true,
  "elements":[
   "_version"
  ]
 },
 "required":{
  "__set__":true,
  "elements":[
   "Cython",
   "black",
   "cffi",
   "numba",
   "numpy",
   "pytest",
   "randomgen",
   "setuptools",
   "versioneer"
  ]
 }
}