{
 "builtin":{
  "__set__":true,
  "elements":[
   "argparse",
   "collections",
   "configparser",
   "copy",
   "datetime",
   "distutils",
   "functools",
   "getpass",
   "glob",
   "gzip",
   "io",
   "json",
   "math",
   "optparse",
   "os",
   "pprint",
   "re",
   "shutil",
   "sqlite3",
   "sys",
   "tarfile",
   "tempfile",
   "urllib"
  ]
 },
 "relative":{
  "__set__":true,
  "elements":[
   "proj",
   "tensor"
  ]
 },
 "required":{
  "__set__":true,
  "elements":[
   "fiona",
   "libcomcat",
   "mapio",
   "numpy",
   "obspy",
   "pandas",
   "pyproj",
   "shapely",
   "strec"
  ]
 }
}