{
 "builtin":{
  "__set__":true,
  "elements":[
   "__future__",
   "datetime",
   "decimal",
   "filecmp",
   "io",
   "os",
   "re",
   "struct",
   "sys",
   "tempfile",
   "time",
   "unittest"
  ]
 },
 "relative":{
  "__set__":true,
  "elements":[
   "BIFFRecords",
   "Cell",
   "Column",
   "ExcelFormula",
   "ExcelMagic",
   "Formatting",
   "Row",
   "Style",
   "UnicodeUtils",
   "Workbook",
   "Worksheet",
   "antlr",
   "compat"
  ]
 },
 "required":{
  "__set__":true,
  "elements":[
   "pkginfo",
   "pyExcelerator",
   "setuptools",
   "utils",
   "xlwt"
  ]
 }
}